{
  "display": {
    "icon": {
      "item": "minecraft:stone"
    },
    "title": {
      "translate": "advancements.stone.title"
    },
    "description": {
      "translate": "advancements.stone.descr"
    },
    "frame": "task",
    "show_toast": true,
    "announce_to_chat": true,
    "hidden": false
  },
  "criteria": {
    "stone": {
      "trigger": "minecraft:placed_block",
      "conditions": {
        "location": [
          {
            "block": "minecraft:stone",
            "condition": "minecraft:block_state_property"
          }
        ]
      }
    }
  },
  "rewards": {
    "experience": 30
  },
  "parent": "moreadvancements:cobble"
}